cellmake/__init__.py
cellmake-0.0.2.dist-info/LICENSE
cellmake-0.0.2.dist-info/WHEEL
cellmake-0.0.2.dist-info/METADATA
cellmake-0.0.2.dist-info/RECORD
