Metadata-Version: 2.1
Name: cellmake
Version: 0.0.2
Summary: A Python package for single-cell RNA-sequencing data analysis.
Author-email: Malte Kuehl <malte.kuehl@clin.au.dk>
Classifier: License :: OSI Approved :: GNU General Public License v3 or later (GPLv3+)
Project-URL: Home, https://github.com/complextissue/
